CHANGES.rst
INSTALL.rst
LICENSE.txt
MANIFEST.in
README.rst
setup.py
beatboxtestbed/__init__.py
beatboxtestbed/_console.py
beatboxtestbed/beatbox.py
beatboxtestbed/cycling.py
beatboxtestbed/helpers.py
beatboxtestbed/multimox.py
beatboxtestbed/plotting.py
beatboxtestbed.egg-info/PKG-INFO
beatboxtestbed.egg-info/SOURCES.txt
beatboxtestbed.egg-info/dependency_links.txt
beatboxtestbed.egg-info/entry_points.txt
beatboxtestbed.egg-info/not-zip-safe
beatboxtestbed.egg-info/requires.txt
beatboxtestbed.egg-info/top_level.txt
beatboxtestbed/data/settings.cfg
examples/manuscript.py
examples/settings_CH2Oac.cfg
examples/settings_CH2Onc.cfg
examples/settings_NO2ac.cfg
examples/settings_NO2nc.cfg