Metadata-Version: 1.1
Name: beatboxtestbed
Version: 1.0.0
Summary: background error analysis testbed with box models
Home-page: https://boxmodeling.meteo.physik.uni-muenchen.de
Author: Christoph Knote, Jerome Barre
Author-email: christoph.knote@physik.uni-muenchen.de, barre@ucar.edu
License: GPLv3
Platform: UNKNOWN
Classifier: Development Status :: 5 - Production/Stable
Classifier: Environment :: Console
Classifier: Intended Audience :: Developers
Classifier: Intended Audience :: Education
Classifier: Intended Audience :: End Users/Desktop
Classifier: Intended Audience :: Science/Research
Classifier: License :: OSI Approved :: GNU General Public License v3 (GPLv3)
Classifier: Operating System :: POSIX
Classifier: Programming Language :: Python :: 2 :: Only
Classifier: Topic :: Education
Classifier: Topic :: Scientific/Engineering
Classifier: Topic :: Utilities
